[
  {
    "id": 2342,
    "name": "earth",
    "full_name": "Sol/earth",
    "html_url": "https://github.instance/Sol/earth",
    "description": "Earth is the third planet from the Sun and the home-world of humanity.",
    "created_at": "2017-01-31T09:39:12Z",
    "updated_at": "2020-10-07T09:42:53Z",
    "pushed_at": "2020-10-08T12:18:22Z",
    "stargazers_count": 136,
    "watchers_count": 136,
    "language": "JavaScript",
    "forks_count": 331,
    "open_issues_count": 98,
    "license": null,
    "default_branch": "master",
    "owner": {
      "login": "Sol",
      "avatar_url": "./images/demo/Sol.png"
    },
    "_InnerSourceMetadata": {
      "participation": [
        15,
        3,
        7,
        2,
        7,
        6,
        11,
        4,
        9,
        11,
        4,
        0,
        4,
        6,
        3,
        2,
        6,
        4,
        3,
        5,
        9,
        1,
        2,
        2,
        7,
        6,
        7,
        25,
        9,
        7,
        9,
        10,
        7,
        3,
        8,
        10,
        13,
        6,
        5,
        4,
        9,
        6,
        8,
        8,
        10,
        3,
        3,
        6,
        2,
        8,
        12,
        8
      ],
      "logo": "./images/demo/Earth.png",
      "score": 3900,
      "topics": [
        "earth",
        "JavaScript",
        "Sol"
      ]
    }
  },
  {
    "id": 4711,
    "name": "mars",
    "full_name": "Mars/mars",
    "html_url": "https://github.instance/Mars/mars",
    "description": "Mars is the fourth planet from the Sun and the second-smallest planet in the Solar System, being larger than only Mercury.",
    "created_at": "2019-02-19T07:49:05Z",
    "updated_at": "2020-10-08T11:27:06Z",
    "pushed_at": "2020-10-08T13:35:04Z",
    "stargazers_count": 56,
    "watchers_count": 56,
    "language": "Groovy",
    "forks_count": 33,
    "open_issues_count": 3,
    "license": null,
    "default_branch": "master",
    "owner": {
      "login": "Mars",
      "avatar_url": "./images/demo/Mars.png"
    },
    "_InnerSourceMetadata": {
      "participation": [
        2,
        5,
        12,
        7,
        1,
        0,
        3,
        0,
        1,
        1,
        3,
        0,
        5,
        2,
        6,
        3,
        19,
        14,
        8,
        9,
        4,
        16,
        3,
        98,
        24,
        28,
        7,
        15,
        18,
        10,
        45,
        73,
        61,
        15,
        0,
        18,
        42,
        35,
        33,
        25,
        6,
        20,
        66,
        10,
        11,
        9,
        7,
        0,
        2,
        4,
        9,
        2
      ],
      "title": "Mars",
      "motivation": "Mars can easily be seen from Earth with the naked eye, as can its reddish coloring.",
      "contributions": [
        "Good practices",
        "Tutorials",
        "Tips & tricks",
        "How tos",
        "News",
        "Examples"
      ],
      "skills": [
        "Java",
        "Javascript",
        "Node.js",
        "C++"
      ],
      "logo": "./images/demo/Mars.png",
      "score": 3767,
      "topics": [
        "mars",
        "Groovy",
        "Mars",
        "some",
        "more",
        "topics",
        "that",
        "describe",
        "this",
        "repo",
        "a",
        "little",
        "more"
      ]
    }
  },
  {
    "id": 7093,
    "name": "ceres",
    "full_name": "Belt/ceres",
    "html_url": "https://github.instance/Belt/ceres",
    "description": "Ceres is the largest object in the main asteroid belt that lies between the orbits of Mars and Jupiter.",
    "created_at": "2017-01-20T09:46:40Z",
    "updated_at": "2020-10-08T12:55:38Z",
    "pushed_at": "2020-10-08T15:47:54Z",
    "stargazers_count": 30,
    "watchers_count": 30,
    "language": "TypeScript",
    "forks_count": 20,
    "open_issues_count": 157,
    "license": null,
    "default_branch": "master",
    "owner": {
      "login": "Belt",
      "avatar_url": "./images/demo/Ceres.png"
    },
    "_InnerSourceMetadata": {
      "participation": [
        38,
        38,
        71,
        96,
        87,
        87,
        27,
        26,
        30,
        29,
        8,
        0,
        20,
        29,
        36,
        47,
        46,
        71,
        76,
        50,
        54,
        57,
        49,
        34,
        67,
        81,
        91,
        82,
        64,
        56,
        70,
        72,
        55,
        29,
        39,
        30,
        58,
        68,
        40,
        46,
        20,
        21,
        36,
        15,
        13,
        42,
        29,
        67,
        96,
        102,
        81,
        45
      ],
      "score": 2655
    }
  },
  {
    "id": 6969,
    "name": "ve_nus",
    "full_name": "Sol/venus",
    "html_url": "https://github.instance/Sol/venus",
    "description": "Venus is the second planet from the Sun. It is named after the Roman goddess of love and beauty.",
    "created_at": "2018-08-10T05:47:37Z",
    "updated_at": "2020-10-07T17:02:33Z",
    "pushed_at": "2020-10-08T14:32:15Z",
    "stargazers_count": 20,
    "watchers_count": 20,
    "language": "C++",
    "forks_count": 29,
    "open_issues_count": 10,
    "license": null,
    "default_branch": "master",
    "owner": {
      "login": "Sol",
      "avatar_url": "./images/demo/Sol.png"
    },
    "_InnerSourceMetadata": {
      "title": "Venus",
      "motivation": "Venus lies within Earth's orbit, and so never appears to venture far from the Sun, either setting in the west just after dusk or rising in the east a bit before dawn.",
      "contributions": [
        "Documentation",
        "Bugfixes",
        "Features"
      ],
      "skills": [
        "C++",
        "Markdown"
      ],
      "logo": "./images/demo/Venus.png",
      "guidelines": "CONTRIBUTING.md",
      "participation": [
        13,
        7,
        8,
        2,
        4,
        8,
        9,
        5,
        3,
        4,
        4,
        1,
        3,
        5,
        5,
        4,
        6,
        8,
        13,
        4,
        5,
        6,
        6,
        7,
        5,
        9,
        7,
        8,
        6,
        5,
        9,
        6,
        8,
        8,
        13,
        5,
        4,
        6,
        7,
        17,
        10,
        5,
        7,
        12,
        4,
        4,
        6,
        6,
        5,
        7,
        5,
        4
      ],
      "score": 1635,
      "topics": [
      ]
    }
  },
  {
    "id": 2222,
    "name": "titan",
    "full_name": "Saturn/titan",
    "html_url": "https://github.instance/Saturn/titan",
    "description": "Titan is the largest moon of Saturn and the second-largest natural satellite in the Solar System. It is the only moon known to have a dense atmosphere, and the only known body in space, other than Earth, where clear evidence of stable bodies of surface liquid has been found.",
    "created_at": "2019-08-07T13:48:29Z",
    "updated_at": "2020-10-07T13:54:43Z",
    "pushed_at": "2020-10-07T13:51:18Z",
    "stargazers_count": 11,
    "watchers_count": 47,
    "language": "Java",
    "forks_count": 23,
    "open_issues_count": 42,
    "license": null,
    "default_branch": "master",
    "owner": {
      "login": "Saturn",
      "avatar_url": "./images/demo/Saturn.png"
    },
    "_InnerSourceMetadata": {
      "participation": [
        0,
        0,
        0,
        0,
        0,
        0,
        0,
        0,
        0,
        0,
        0,
        0,
        0,
        0,
        0,
        0,
        0,
        0,
        0,
        0,
        0,
        0,
        0,
        0,
        0,
        0,
        5,
        15,
        34,
        25,
        14,
        28,
        5,
        0,
        1,
        0,
        0,
        0,
        0,
        1,
        3,
        0,
        0,
        0,
        0,
        0,
        0,
        0,
        0,
        0,
        0,
        0
      ],
      "logo": "./images/demo/Titan.png",
      "score": 1168,
      "topics": [
        "titan",
        "Java",
        "Saturn"
      ]
    }
  },
  {
    "id": 376172,
    "name": "Phoebe",
    "full_name": "Saturn/phoebe",
    "html_url": "https://github.instance/Saturn/phoebe",
    "description": "Phoebe is an irregular satellite of Saturn. It was spherical and hot early in its history and was battered out of roundness by repeated impacts.",
    "created_at": "2020-07-01T07:58:11Z",
    "updated_at": "2020-10-08T12:29:18Z",
    "pushed_at": "2020-10-08T12:29:14Z",
    "stargazers_count": 3,
    "watchers_count": 3,
    "language": "JavaScript",
    "forks_count": 3,
    "open_issues_count": 2,
    "license": null,
    "default_branch": "master",
    "owner": {
      "login": "Saturn",
      "avatar_url": "./images/demo/Phoebe.png"
    },
    "_InnerSourceMetadata": {
      "participation": [
        0,
        0,
        0,
        0,
        0,
        0,
        0,
        0,
        0,
        0,
        0,
        0,
        0,
        0,
        0,
        0,
        0,
        0,
        0,
        0,
        0,
        0,
        0,
        0,
        0,
        0,
        0,
        0,
        0,
        0,
        0,
        0,
        0,
        0,
        0,
        0,
        0,
        4,
        67,
        13,
        8,
        8,
        26,
        78,
        17,
        7,
        7,
        7,
        7,
        13,
        16,
        2
      ],
      "contributions": [
        "Any"
      ],
      "skills": [
        "node.js",
        "travis",
        "GitHub"
      ],
      "logo": "./images/demo/Phoebe.png",
      "score": 1140,
      "topics": [
        "Phoebe",
        "JavaScript",
        "Saturn"
      ]
    }
  },
  {
    "id": 1993,
    "name": "europa",
    "full_name": "Jupiter/europa",
    "html_url": "https://github.instance/Jupiter/europa",
    "description": "Europa is the smallest of the four Galilean moons orbiting Jupiter, and the sixth-closest to the planet of all the 79 known moons of Jupiter.",
    "watchers_count": 0,
    "stargazers_count": 1,
    "open_issues_count": 19,
    "forks_count": 20,
    "owner": {
      "login": "Jupiter",
      "avatar_url": "./images/demo/Europa.png"
    },
    "_InnerSourceMetadata": {
      "participation": [
        17,
        6,
        11,
        7,
        2,
        12,
        10,
        1,
        6,
        11,
        5,
        0,
        1,
        12,
        6,
        1,
        3,
        9,
        8,
        21,
        13,
        3,
        6,
        14,
        30,
        16,
        14,
        6,
        4,
        0,
        3,
        9,
        3,
        1,
        7,
        2,
        4,
        5,
        7,
        0,
        7,
        2,
        6,
        9,
        3,
        4,
        3,
        1,
        1,
        4,
        4,
        3
      ],
      "score": 1074,
      "topics": [
        "europa",
        null,
        "Jupiter"
      ]
    },
    "updated_at": "2020-10-08T12:13:40.000Z",
    "created_at": "2019-10-08T15:49:15.880Z"
  },
  {
    "id": "0815",
    "name": "neptune",
    "full_name": "Sol/neptune",
    "html_url": "https://github.instance/Sol/neptune",
    "description": "Neptune is the eighth and farthest-known Solar planet from the Sun. In the Solar System, it is the fourth-largest planet by diameter, the third-most-massive planet, and the densest giant planet.",
    "created_at": "2020-08-03T10:56:05Z",
    "updated_at": "2020-10-01T06:41:07Z",
    "pushed_at": "2020-10-01T06:41:04Z",
    "stargazers_count": 1,
    "watchers_count": 1,
    "language": null,
    "forks_count": 0,
    "open_issues_count": 0,
    "license": null,
    "default_branch": "master",
    "owner": {
      "login": "Sol",
      "avatar_url": "./images/demo/Sol.png"
    },
    "_InnerSourceMetadata": {
      "participation": [
        0,
        0,
        0,
        0,
        0,
        0,
        0,
        0,
        0,
        0,
        0,
        0,
        0,
        0,
        0,
        0,
        0,
        0,
        0,
        0,
        0,
        0,
        0,
        0,
        0,
        0,
        0,
        0,
        0,
        0,
        0,
        0,
        0,
        0,
        0,
        0,
        0,
        0,
        0,
        0,
        0,
        0,
        22,
        7,
        3,
        9,
        0,
        4,
        0,
        0,
        0,
        1
      ],
      "contributions": [
        "Links",
        "Blog posts",
        "Presentations"
      ],
      "skills": [
        "markdown"
      ],
      "language": "Markdown",
      "score": 907,
      "logo": "./images/demo/Neptune.png",
      "topics": [
        "neptune",
        null,
        "Sol"
      ]
    }
  },
  {
    "id": 86209,
    "name": "auberon",
    "full_name": "Colony/auberon",
    "html_url": "https://github.instance/Colony/auberon",
    "description": "Auberon is a planet that has a lush biome that grows native and Terran crops.",
    "updated_at": "2020-10-08T08:54:39.000Z",
    "created_at": "2019-10-08T15:49:15.877Z",
    "watchers_count": 0,
    "stargazers_count": 2,
    "open_issues_count": 23,
    "forks_count": 5,
    "license": null,
    "language": "Go",
    "default_branch": "master",
    "owner": {
      "login": "Colony",
      "avatar_url": "./images/demo/Auberon.png"
    },
    "_InnerSourceMetadata": {
      "contributions": [
        "Commands",
        "Bugfixes",
        "Improvements"
      ],
      "skills": [
        "Go",
        "Java",
        "Spring"
      ],
      "docs": "https://expanse.fandom.com/wiki/Auberon",
      "participation": [
        3,
        12,
        10,
        8,
        9,
        16,
        6,
        17,
        7,
        21,
        7,
        0,
        6,
        20,
        17,
        18,
        8,
        7,
        5,
        24,
        5,
        8,
        7,
        14,
        11,
        13,
        10,
        29,
        18,
        25,
        5,
        9,
        7,
        3,
        5,
        3,
        0,
        7,
        3,
        5,
        3,
        12,
        0,
        1,
        3,
        0,
        4,
        5,
        7,
        3,
        12,
        14
      ],
      "score": 728,
      "topics": [
        "auberon",
        "Go",
        "Colony"
      ]
    }
  },
  {
    "id": 6175,
    "name": "uranus",
    "full_name": "Sol/uranus",
    "html_url": "https://github.instance/Sol/uranus",
    "description": "Uranus is the seventh planet from the Sun. Its name is a reference to the Greek god of the sky.",
    "created_at": "2019-12-05T06:38:57Z",
    "updated_at": "2020-09-28T20:58:14Z",
    "pushed_at": "2020-09-28T20:58:10Z",
    "stargazers_count": 0,
    "watchers_count": 0,
    "language": "JavaScript",
    "forks_count": 1,
    "open_issues_count": 12,
    "license": null,
    "default_branch": "master",
    "owner": {
      "login": "Sol",
      "avatar_url": "./images/demo/Sol.png"
    },
    "_InnerSourceMetadata": {
      "participation": [
        0,
        0,
        0,
        0,
        0,
        0,
        0,
        0,
        1,
        0,
        0,
        0,
        0,
        0,
        0,
        0,
        3,
        44,
        37,
        81,
        86,
        34,
        9,
        3,
        32,
        44,
        54,
        38,
        7,
        0,
        0,
        0,
        0,
        3,
        0,
        4,
        0,
        5,
        1,
        0,
        2,
        0,
        2,
        6,
        1,
        0,
        1,
        0,
        0,
        0,
        2,
        0
      ],
      "contributions": [
        "Bugfixes",
        "Features",
        "User Experience",
        "Documentation"
      ],
      "skills": [
        "Vue.js",
        "Node.js",
        "Postgres"
      ],
      "logo": "./images/demo/Uranus.png",
      "score": 672,
      "topics": [
        "uranus",
        "JavaScript",
        "Sol"
      ]
    }
  },
  {
    "id": 8759,
    "name": "herculina",
    "full_name": "Belt/herculina",
    "html_url": "https://github.instance/Belt/herculina",
    "description": "Herculina is one of the larger members of the main asteroid belt.",
    "created_at": "2020-03-19T10:48:45Z",
    "updated_at": "2020-10-01T14:30:49Z",
    "pushed_at": "2020-10-01T14:41:06Z",
    "stargazers_count": 1,
    "watchers_count": 1,
    "language": "Dockerfile",
    "forks_count": 6,
    "open_issues_count": 0,
    "license": null,
    "default_branch": "master",
    "owner": {
      "login": "Belt",
      "avatar_url": "./images/demo/Herculina.png"
    },
    "_InnerSourceMetadata": {
      "participation": [
        0,
        0,
        0,
        0,
        0,
        0,
        0,
        0,
        0,
        0,
        0,
        0,
        0,
        0,
        0,
        0,
        0,
        0,
        0,
        0,
        0,
        6,
        1,
        9,
        0,
        1,
        0,
        0,
        4,
        0,
        0,
        0,
        7,
        0,
        0,
        1,
        3,
        0,
        0,
        0,
        0,
        0,
        1,
        4,
        8,
        3,
        0,
        0,
        6,
        0,
        1,
        2
      ],
      "score": 615,
      "topics": [
        "herculina",
        "Dockerfile",
        "Belt"
      ]
    }
  },
  {
    "id": 1610,
    "name": "ganymede",
    "full_name": "Jupiter/ganymede",
    "html_url": "https://github.instance/Jupiter/ganymede",
    "description": "Ganymede is the largest and most massive of the Solar System's moons.",
    "created_at": "2016-05-23T08:48:14Z",
    "updated_at": "2020-10-01T11:46:15Z",
    "pushed_at": "2020-03-16T08:05:37Z",
    "stargazers_count": 94,
    "watchers_count": 94,
    "language": "JavaScript",
    "forks_count": 18,
    "open_issues_count": 31,
    "license": null,
    "default_branch": "master",
    "owner": {
      "login": "Jupiter",
      "avatar_url": "./images/demo/Jupiter.png"
    },
    "_InnerSourceMetadata": {
      "participation": [
        0,
        0,
        0,
        0,
        0,
        0,
        0,
        0,
        0,
        0,
        0,
        0,
        0,
        0,
        0,
        0,
        15,
        12,
        0,
        0,
        0,
        5,
        2,
        0,
        0,
        0,
        0,
        0,
        0,
        0,
        0,
        0,
        0,
        0,
        0,
        0,
        0,
        0,
        0,
        0,
        0,
        0,
        0,
        0,
        0,
        0,
        0,
        0,
        0,
        0,
        0,
        0
      ],
      "logo": "./images/demo/Ganymede.png",
      "score": 524,
      "topics": [
        "ganymede",
        "JavaScript",
        "Jupiter"
      ]
    }
  },
  {
    "id": 1022,
    "name": "luna",
    "full_name": "Sol/luna",
    "html_url": "https://github.instance/Sol/luna",
    "description": "Moon is an astronomical body orbiting Earth and is the planet's only natural satellite.",
    "created_at": "2019-11-13T16:28:53Z",
    "updated_at": "2020-10-08T15:30:40Z",
    "pushed_at": "2020-10-08T15:47:15Z",
    "stargazers_count": 3,
    "watchers_count": 3,
    "language": "Java",
    "forks_count": 5,
    "open_issues_count": 1,
    "license": null,
    "default_branch": "master",
    "owner": {
      "login": "Sol",
      "avatar_url": "./images/demo/Luna.png"
    },
    "_InnerSourceMetadata": {
      "participation": [
        0,
        6,
        3,
        0,
        2,
        0,
        0,
        0,
        0,
        0,
        0,
        0,
        0,
        2,
        0,
        0,
        0,
        1,
        2,
        1,
        0,
        0,
        8,
        12,
        10,
        4,
        9,
        2,
        8,
        1,
        1,
        5,
        0,
        4,
        1,
        0,
        10,
        9,
        2,
        9,
        19,
        1,
        2,
        9,
        8,
        4,
        1,
        2,
        2,
        0,
        2,
        11
      ],
      "score": 428,
      "topics": [
        "luna",
        "Java",
        "Sol"
      ]
    }
  },
  {
    "id": 6161,
    "name": "laconia",
    "full_name": "Colony/laconia",
    "html_url": "https://github.instance/Colony/laconia",
    "description": "Laconia is an evil planet in the system with the same name.",
    "created_at": "2016-05-12T13:28:39Z",
    "updated_at": "2020-10-01T11:46:21Z",
    "pushed_at": "2020-02-03T12:09:52Z",
    "stargazers_count": 27,
    "watchers_count": 27,
    "language": "JavaScript",
    "forks_count": 3,
    "open_issues_count": 7,
    "license": null,
    "default_branch": "master",
    "owner": {
      "login": "Colony",
      "avatar_url": "./images/demo/Laconia.png"
    },
    "_InnerSourceMetadata": {
      "participation": [
        0,
        0,
        0,
        0,
        0,
        0,
        0,
        0,
        0,
        0,
        0,
        0,
        0,
        0,
        2,
        0,
        19,
        0,
        0,
        0,
        0,
        0,
        0,
        0,
        0,
        0,
        0,
        0,
        0,
        0,
        0,
        0,
        0,
        0,
        0,
        0,
        0,
        0,
        0,
        0,
        0,
        0,
        0,
        0,
        0,
        0,
        0,
        0,
        0,
        0,
        0,
        0
      ],
      "guidelines": "CONTRIBUTING.md",
      "score": 297,
      "topics": [
        "laconia",
        "JavaScript",
        "Colony"
      ]
    }
  },
  {
    "id": 7520,
    "name": "gate",
    "full_name": "Sol/gate",
    "html_url": "https://github.instance/Sol/gate",
    "description": "A wormhole gate that is part of an ancient network built by an alien civilization billions of years ago.",
    "created_at": "2020-05-25T12:05:16Z",
    "updated_at": "2020-07-30T14:58:59Z",
    "pushed_at": "2020-05-25T12:07:10Z",
    "stargazers_count": 0,
    "watchers_count": 0,
    "language": "JavaScript",
    "forks_count": 0,
    "open_issues_count": 0,
    "license": null,
    "default_branch": "master",
    "owner": {
      "login": "Sol",
      "avatar_url": "./images/demo/Sol.png"
    },
    "_InnerSourceMetadata": {
      "participation": [
        0,
        0,
        0,
        0,
        0,
        0,
        2,
        0,
        1,
        0,
        0,
        0,
        0,
        0,
        0,
        0,
        0,
        0,
        0,
        0,
        0,
        0,
        0,
        0,
        2,
        0,
        0,
        0,
        0,
        0,
        0,
        0,
        0,
        0,
        0,
        0,
        0,
        0,
        0,
        0,
        0,
        0,
        0,
        0,
        0,
        0,
        0,
        0,
        0,
        0,
        0,
        0
      ],
      "logo": "./images/demo/Gate.png",
      "score": 268,
      "topics": [
        "gate",
        "JavaScript",
        "Sol"
      ]
    }
  },
  {
    "id": 2921,
    "name": "enceladus",
    "full_name": "Saturn/enceladus",
    "html_url": "https://github.instance/Saturn/enceladus",
    "description": "Enceladus is the sixth-largest moon of Saturn. ",
    "created_at": "2019-07-22T07:52:36Z",
    "updated_at": "2020-10-08T12:12:16Z",
    "pushed_at": "2020-10-08T12:18:03Z",
    "stargazers_count": 2,
    "watchers_count": 2,
    "language": "JavaScript",
    "forks_count": 0,
    "open_issues_count": 0,
    "license": null,
    "default_branch": "master",
    "owner": {
      "login": "Saturn",
      "avatar_url": "./images/demo/Enceladus.png"
    },
    "_InnerSourceMetadata": {
      "participation": [
        10,
        0,
        0,
        0,
        0,
        4,
        6,
        0,
        2,
        0,
        5,
        0,
        8,
        0,
        9,
        12,
        9,
        9,
        5,
        2,
        2,
        1,
        2,
        3,
        5,
        7,
        2,
        5,
        0,
        2,
        0,
        8,
        3,
        3,
        12,
        3,
        9,
        7,
        0,
        4,
        1,
        10,
        2,
        18,
        9,
        4,
        9,
        5,
        2,
        1,
        0,
        1
      ],
      "score": 262,
      "topics": [
        "enceladus",
        "JavaScript",
        "Saturn"
      ]
    }
  },
  {
    "id": 2883,
    "name": "cyllene",
    "full_name": "Jupiter/cyllene",
    "html_url": "https://github.instance/Jupiter/cyllene",
    "description": "Cyllene, also known as Jupiter XLVIII, is a natural satellite of Jupiter.",
    "created_at": "2018-04-26T16:27:04Z",
    "updated_at": "2020-10-01T15:27:14Z",
    "pushed_at": "2020-10-01T15:27:33Z",
    "stargazers_count": 2,
    "watchers_count": 2,
    "language": "Ruby",
    "forks_count": 4,
    "open_issues_count": 3,
    "license": null,
    "default_branch": "master",
    "owner": {
      "login": "Jupiter",
      "avatar_url": "./images/demo/Cyllene.png"
    },
    "_InnerSourceMetadata": {
      "contributions": [
        "Anything you'd like to see"
      ],
      "skills": [
        "Ruby knowledge is helpful"
      ],
      "participation": [
        8,
        12,
        2,
        0,
        2,
        0,
        0,
        7,
        2,
        0,
        0,
        0,
        0,
        0,
        0,
        1,
        5,
        0,
        0,
        0,
        0,
        1,
        0,
        1,
        1,
        0,
        1,
        6,
        4,
        2,
        2,
        0,
        0,
        0,
        0,
        0,
        16,
        27,
        3,
        0,
        0,
        9,
        11,
        0,
        0,
        3,
        0,
        0,
        5,
        0,
        2,
        5
      ],
      "score": 256,
      "topics": [
        "cyllene",
        "Ruby",
        "Jupiter"
      ]
    }
  },
  {
    "id": 2674,
    "name": "sol",
    "full_name": "Sol/sol",
    "html_url": "https://github.instance/Sol/sol",
    "description": "The Sun is the star at the center of the Solar System.",
    "created_at": "2019-04-30T04:11:11Z",
    "updated_at": "2020-08-07T07:06:15Z",
    "pushed_at": "2020-10-02T13:41:37Z",
    "stargazers_count": 6,
    "watchers_count": 6,
    "language": null,
    "forks_count": 1,
    "open_issues_count": 10,
    "license": null,
    "default_branch": "master",
    "owner": {
      "login": "Sol",
      "avatar_url": "./images/demo/Sol.png"
    },
    "_InnerSourceMetadata": {
      "guidelines": "CONTRIBUTING.md",
      "participation": [
        0,
        0,
        0,
        4,
        12,
        2,
        1,
        0,
        5,
        0,
        1,
        0,
        11,
        0,
        1,
        1,
        0,
        5,
        2,
        0,
        0,
        0,
        0,
        7,
        1,
        1,
        0,
        0,
        0,
        0,
        1,
        0,
        0,
        1,
        0,
        0,
        0,
        5,
        5,
        4,
        7,
        2,
        0,
        2,
        0,
        0,
        0,
        0,
        0,
        0,
        0,
        0
      ],
      "score": 220,
      "topics": [
        "sol",
        null,
        "Sol"
      ]
    }
  },
  {
    "id": 1675,
    "name": "saturn",
    "full_name": "Saturn/saturn",
    "html_url": "https://github.instance/Saturn/saturn",
    "description": "Saturn's famous feature is its prominent ring system, which is composed mostly of ice particles, with a smaller amount of rocky debris and dust.",
    "created_at": "2019-01-28T13:53:19Z",
    "updated_at": "2020-09-30T12:12:36Z",
    "pushed_at": "2020-09-30T12:12:32Z",
    "stargazers_count": 0,
    "watchers_count": 0,
    "language": "Shell",
    "forks_count": 1,
    "open_issues_count": 0,
    "license": null,
    "default_branch": "master",
    "owner": {
      "login": "Saturn",
      "avatar_url": "./images/demo/Saturn.png"
    },
    "_InnerSourceMetadata": {
      "participation": [
        0,
        0,
        6,
        7,
        2,
        1,
        15,
        2,
        4,
        7,
        0,
        0,
        3,
        2,
        3,
        0,
        4,
        3,
        10,
        4,
        20,
        2,
        2,
        0,
        2,
        0,
        0,
        1,
        0,
        1,
        2,
        1,
        2,
        7,
        7,
        0,
        2,
        4,
        0,
        2,
        4,
        0,
        2,
        5,
        5,
        3,
        6,
        4,
        9,
        2,
        2,
        0
      ],
      "score": 219,
      "topics": [
        "saturn",
        "Shell",
        "Saturn"
      ]
    }
  },
  {
    "id": 11924,
    "name": "naraka",
    "full_name": "Colony/naraka",
    "html_url": "https://github.instance/Colony/naraka",
    "description": "The Naraka system is a dead system connected to the Ring network.",
    "created_at": "2019-12-12T15:36:31Z",
    "updated_at": "2020-04-23T06:27:45Z",
    "pushed_at": "2020-03-02T14:52:24Z",
    "stargazers_count": 5,
    "watchers_count": 5,
    "language": "Scala",
    "forks_count": 0,
    "open_issues_count": 0,
    "license": null,
    "default_branch": "master",
    "owner": {
      "login": "Colony",
      "avatar_url": "./images/demo/Naraka.png"
    },
    "_InnerSourceMetadata": {
      "participation": [
        0,
        0,
        0,
        0,
        0,
        0,
        0,
        0,
        0,
        1,
        4,
        0,
        0,
        10,
        9,
        10,
        9,
        1,
        1,
        3,
        15,
        0,
        0,
        0,
        0,
        0,
        0,
        0,
        0,
        0,
        0,
        0,
        0,
        0,
        0,
        0,
        0,
        0,
        0,
        0,
        0,
        0,
        0,
        0,
        0,
        0,
        0,
        0,
        0,
        0,
        0,
        0
      ],
      "guidelines": "CONTRIBUTING.md",
      "score": 191,
      "topics": [
        "naraka",
        "Scala",
        "Colony"
      ]
    }
  },
  {
    "id": 2459,
    "name": "pallas",
    "full_name": "Belt/pallas",
    "html_url": "https://github.instance/Belt/pallas",
    "description": "Pallas is the second asteroid to have been discovered, after 1 Ceres.",
    "created_at": "2017-04-05T13:59:20Z",
    "updated_at": "2020-10-02T10:58:47Z",
    "pushed_at": "2018-07-26T07:03:32Z",
    "stargazers_count": 3,
    "watchers_count": 3,
    "language": "JavaScript",
    "forks_count": 8,
    "open_issues_count": 0,
    "license": null,
    "default_branch": "master",
    "owner": {
      "login": "Belt",
      "avatar_url": "./images/demo/Pallas.png"
    },
    "_InnerSourceMetadata": {
      "participation": [
        0,
        0,
        0,
        0,
        0,
        0,
        0,
        0,
        0,
        0,
        0,
        0,
        0,
        0,
        0,
        0,
        0,
        0,
        0,
        0,
        0,
        0,
        0,
        0,
        0,
        0,
        0,
        0,
        0,
        0,
        0,
        0,
        0,
        0,
        0,
        0,
        0,
        0,
        0,
        0,
        0,
        0,
        0,
        0,
        0,
        0,
        0,
        0,
        0,
        0,
        0,
        0
      ],
      "score": 182,
      "topics": [
        "pallas",
        "JavaScript",
        "Belt"
      ]
    }
  },
  {
    "id": 1671,
    "name": "iapetus",
    "full_name": "Saturn/iapetus",
    "html_url": "https://github.instance/Saturn/iapetus",
    "description": "Iapetus is the third-largest natural satellite of Saturn, eleventh-largest in the Solar System.",
    "created_at": "2019-10-09T11:44:11Z",
    "updated_at": "2020-07-02T11:22:51Z",
    "pushed_at": "2020-07-02T11:22:47Z",
    "stargazers_count": 0,
    "watchers_count": 0,
    "language": null,
    "forks_count": 6,
    "open_issues_count": 2,
    "license": null,
    "default_branch": "master",
    "owner": {
      "login": "Saturn",
      "avatar_url": "./images/demo/Iapetus.png"
    },
    "_InnerSourceMetadata": {
      "guidelines": "CONTRIBUTING.md",
      "participation": [
        4,
        0,
        0,
        0,
        0,
        0,
        6,
        2,
        5,
        5,
        0,
        0,
        0,
        0,
        0,
        0,
        0,
        0,
        0,
        0,
        0,
        0,
        0,
        0,
        0,
        0,
        0,
        0,
        0,
        0,
        0,
        0,
        0,
        0,
        0,
        0,
        0,
        0,
        1,
        0,
        0,
        0,
        0,
        0,
        0,
        0,
        0,
        0,
        0,
        0,
        0,
        0
      ],
      "contributions": [
        "Documentation",
        "Concept"
      ],
      "score": 182,
      "topics": [
        "iapetus",
        null,
        "Saturn"
      ]
    }
  },
  {
    "id": 290422,
    "name": "hygiea",
    "full_name": "Belt/hygiea",
    "html_url": "https://github.instance/Belt/hygiea",
    "description": null,
    "created_at": "2019-07-15T13:26:41Z",
    "updated_at": "2020-10-05T06:00:19Z",
    "pushed_at": "2020-10-07T05:14:13Z",
    "stargazers_count": 2,
    "watchers_count": 2,
    "language": "JavaScript",
    "forks_count": 4,
    "open_issues_count": 7,
    "license": null,
    "default_branch": "main",
    "owner": {
      "login": "Belt",
      "avatar_url": "./images/demo/Hygiea.png"
    },
    "_InnerSourceMetadata": {
      "participation": [
        13,
        4,
        10,
        0,
        0,
        4,
        0,
        8,
        4,
        0,
        0,
        0,
        0,
        5,
        0,
        3,
        3,
        2,
        0,
        0,
        0,
        0,
        0,
        6,
        5,
        5,
        7,
        2,
        1,
        5,
        0,
        0,
        3,
        0,
        1,
        0,
        0,
        0,
        0,
        1,
        1,
        4,
        2,
        0,
        0,
        3,
        3,
        0,
        0,
        0,
        0,
        2
      ],
      "score": 177,
      "topics": [
        "hygiea",
        "JavaScript",
        "Belt"
      ]
    }
  },
  {
    "id": 6697,
    "name": "mercury",
    "full_name": "Sol/mercury",
    "html_url": "https://github.instance/Sol/mercury",
    "description": "Mercury is the smallest and innermost planet in the Solar System.",
    "created_at": "2019-08-13T13:38:10Z",
    "updated_at": "2020-08-26T11:35:51Z",
    "pushed_at": "2020-08-26T11:44:06Z",
    "stargazers_count": 6,
    "watchers_count": 6,
    "language": "TypeScript",
    "forks_count": 3,
    "open_issues_count": 1,
    "license": null,
    "default_branch": "master",
    "owner": {
      "login": "Sol",
      "avatar_url": "./images/demo/Sol.png"
    },
    "_InnerSourceMetadata": {
      "participation": [
        0,
        0,
        2,
        0,
        0,
        0,
        1,
        1,
        1,
        5,
        6,
        0,
        3,
        0,
        0,
        4,
        2,
        0,
        0,
        3,
        0,
        0,
        0,
        0,
        0,
        2,
        0,
        0,
        0,
        0,
        6,
        2,
        0,
        0,
        0,
        2,
        0,
        1,
        5,
        2,
        1,
        0,
        0,
        0,
        4,
        4,
        0,
        0,
        0,
        0,
        0,
        0
      ],
      "logo": "./images/demo/Mercury.png",
      "score": 132,
      "topics": [
        "mercury",
        "TypeScript",
        "Sol"
      ]
    }
  },
  {
    "id": 24576,
    "name": "hungaria",
    "full_name": "Belt/hungaria",
    "html_url": "https://github.instance/Belt/hungaria",
    "description": "Hungaria is a relatively small asteroid orbiting in the inner asteroid belt.",
    "created_at": "2019-06-14T15:52:40Z",
    "updated_at": "2020-09-22T15:19:52Z",
    "pushed_at": "2020-09-30T13:24:55Z",
    "stargazers_count": 3,
    "watchers_count": 3,
    "language": "Go",
    "forks_count": 1,
    "open_issues_count": 2,
    "license": null,
    "default_branch": "master",
    "owner": {
      "login": "Belt",
      "avatar_url": "./images/demo/Hungaria.png"
    },
    "_InnerSourceMetadata": {
      "participation": [
        0,
        0,
        1,
        0,
        1,
        8,
        7,
        4,
        0,
        0,
        0,
        0,
        1,
        0,
        0,
        0,
        0,
        0,
        0,
        1,
        0,
        0,
        1,
        3,
        0,
        2,
        0,
        1,
        5,
        0,
        0,
        0,
        2,
        0,
        1,
        0,
        0,
        0,
        0,
        3,
        3,
        0,
        3,
        0,
        0,
        0,
        3,
        0,
        0,
        1,
        0,
        0
      ],
      "score": 120,
      "topics": [
        "hungaria",
        "Go",
        "Belt"
      ]
    }
  },
  {
    "id": 300309,
    "name": "eros",
    "full_name": "Belt/eros",
    "html_url": "https://github.instance/Belt/eros",
    "description": "Eros is a stony and elongated asteroid of the Amor group.",
    "created_at": "2019-08-22T12:14:01Z",
    "updated_at": "2020-05-07T16:55:03Z",
    "pushed_at": "2020-03-03T10:39:26Z",
    "stargazers_count": 6,
    "watchers_count": 6,
    "language": "JavaScript",
    "forks_count": 2,
    "open_issues_count": 5,
    "license": null,
    "default_branch": "master",
    "owner": {
      "login": "Belt",
      "avatar_url": "./images/demo/Eros.png"
    },
    "_InnerSourceMetadata": {
      "participation": [
        30,
        21,
        0,
        14,
        0,
        1,
        0,
        4,
        2,
        0,
        10,
        9,
        4,
        7,
        3,
        0,
        2,
        0,
        0,
        0,
        2,
        0,
        0,
        0,
        0,
        0,
        0,
        0,
        0,
        0,
        0,
        0,
        0,
        0,
        0,
        0,
        0,
        0,
        0,
        0,
        0,
        0,
        0,
        0,
        0,
        0,
        0,
        0,
        0,
        0,
        0,
        0
      ],
      "score": 109,
      "topics": [
        "eros",
        "JavaScript",
        "Belt"
      ]
    }
  },
  {
    "id": 3050,
    "name": "arcadia",
    "full_name": "Colony/arcadia",
    "html_url": "https://github.instance/Colony/arcadia",
    "description": "The Arcadia system is one of the planetary systems connected to the Ring network. It was colonized by humans after this ancient network of wormhole gates was re-established by the Ring Station.",
    "created_at": "2019-09-10T09:01:30Z",
    "updated_at": "2020-09-23T10:47:10Z",
    "pushed_at": "2019-09-18T09:38:12Z",
    "stargazers_count": 0,
    "watchers_count": 0,
    "language": "JavaScript",
    "forks_count": 1,
    "open_issues_count": 0,
    "license": null,
    "default_branch": "master",
    "owner": {
      "login": "Colony",
      "avatar_url": "./images/demo/Arcadia.png"
    },
    "_InnerSourceMetadata": {
      "participation": [
        0,
        0,
        0,
        0,
        0,
        0,
        0,
        0,
        0,
        0,
        0,
        0,
        0,
        0,
        0,
        0,
        0,
        0,
        0,
        0,
        0,
        0,
        0,
        0,
        0,
        0,
        0,
        0,
        0,
        0,
        0,
        0,
        0,
        0,
        0,
        0,
        0,
        0,
        0,
        0,
        0,
        0,
        0,
        0,
        0,
        0,
        0,
        0,
        0,
        0,
        0,
        0
      ],
      "score": 102,
      "topics": [
        "arcadia",
        "JavaScript",
        "Colony"
      ]
    }
  },
  {
    "id": 7786,
    "name": "Jupiter/io",
    "full_name": "Jupiter/io",
    "html_url": "https://github.instance/Jupiter/io",
    "description": "Io is the innermost and third-largest of the four Galilean moons of the planet Jupiter.",
    "created_at": "2019-07-11T19:57:58Z",
    "updated_at": "2020-08-05T08:25:24Z",
    "pushed_at": "2020-08-05T08:25:21Z",
    "stargazers_count": 0,
    "watchers_count": 0,
    "language": "HTML",
    "forks_count": 0,
    "open_issues_count": 0,
    "license": null,
    "default_branch": "master",
    "owner": {
      "login": "Jupiter",
      "avatar_url": "./images/demo/Jupiter.png"
    },
    "_InnerSourceMetadata": {
      "participation": [
        0,
        0,
        0,
        0,
        0,
        0,
        1,
        0,
        0,
        0,
        0,
        0,
        0,
        1,
        0,
        1,
        0,
        1,
        13,
        1,
        0,
        0,
        0,
        0,
        0,
        0,
        0,
        0,
        0,
        0,
        0,
        0,
        0,
        0,
        1,
        9,
        0,
        0,
        13,
        34,
        16,
        6,
        2,
        0,
        0,
        0,
        0,
        0,
        0,
        0,
        0,
        0
      ],
      "logo": "./images/demo/Io.png",
      "score": 101,
      "topics": [
        "Jupiter/io",
        "HTML",
        "Jupiter"
      ]
    }
  },
  {
    "id": 134340,
    "name": "pluto",
    "full_name": "Sol/pluto",
    "html_url": "https://github.instance/Sol/pluto",
    "description": "Pluto is a dwarf planet in the Kuiper belt, a ring of bodies beyond the orbit of Neptune.",
    "created_at": "2017-11-14T18:41:52Z",
    "updated_at": "2020-07-06T10:22:13Z",
    "pushed_at": "2020-07-06T10:22:08Z",
    "stargazers_count": 6,
    "watchers_count": 6,
    "language": "JavaScript",
    "forks_count": 6,
    "open_issues_count": 3,
    "license": null,
    "default_branch": "master",
    "owner": {
      "login": "Sol",
      "avatar_url": "./images/demo/Sol.png"
    },
    "_InnerSourceMetadata": {
      "participation": [
        0,
        0,
        0,
        0,
        0,
        0,
        0,
        0,
        0,
        0,
        0,
        0,
        0,
        0,
        0,
        0,
        0,
        0,
        0,
        0,
        0,
        0,
        0,
        0,
        0,
        0,
        0,
        0,
        0,
        0,
        0,
        0,
        0,
        0,
        0,
        0,
        0,
        0,
        1,
        0,
        0,
        0,
        0,
        0,
        0,
        0,
        0,
        0,
        0,
        0,
        0,
        0
      ],
      "contributions": [
        "Bugfixes",
        "Features",
        "Code",
        "Documentation"
      ],
      "skills": [
        "Development",
        "UX"
      ],
      "logo": "./images/demo/Pluto.png",
      "score": 94,
      "topics": [
        "pluto",
        "JavaScript",
        "Sol"
      ]
    }
  },
  {
    "id": 160481,
    "name": "eugenia",
    "full_name": "Belt/eugenia",
    "html_url": "https://github.instance/Belt/eugenia",
    "description": "Eugenia is a large asteroid of the asteroid belt.",
    "created_at": "2018-03-09T18:27:35Z",
    "updated_at": "2018-12-06T14:36:54Z",
    "pushed_at": "2018-12-06T14:36:51Z",
    "stargazers_count": 0,
    "watchers_count": 0,
    "language": "Python",
    "forks_count": 6,
    "open_issues_count": 1,
    "license": null,
    "default_branch": "master",
    "owner": {
      "login": "Belt",
      "avatar_url": "./images/demo/Eugenia.png"
    },
    "_InnerSourceMetadata": {
      "participation": [
        0,
        0,
        0,
        0,
        0,
        0,
        0,
        0,
        0,
        0,
        0,
        0,
        0,
        0,
        0,
        0,
        0,
        0,
        0,
        0,
        0,
        0,
        0,
        0,
        0,
        0,
        0,
        0,
        0,
        0,
        0,
        0,
        0,
        0,
        0,
        0,
        0,
        0,
        0,
        0,
        0,
        0,
        0,
        0,
        0,
        0,
        0,
        0,
        0,
        0,
        0,
        0
      ],
      "score": 80,
      "topics": [
        "eugenia",
        "Python",
        "Belt"
      ]
    }
  },
  {
    "id": 30310,
    "name": "ilus",
    "full_name": "Colony/ilus",
    "html_url": "https://github.instance/Colony/ilus",
    "description": "Ilus is a large Earth-like planet, with slightly over one gravity and a thirty-hour day.",
    "created_at": "2018-12-23T15:20:55Z",
    "updated_at": "2020-07-24T13:41:53Z",
    "pushed_at": "2020-07-24T13:41:50Z",
    "stargazers_count": 3,
    "watchers_count": 3,
    "language": "Java",
    "forks_count": 0,
    "open_issues_count": 13,
    "license": null,
    "default_branch": "master",
    "owner": {
      "login": "Colony",
      "avatar_url": "./images/demo/Ilus.png"
    },
    "_InnerSourceMetadata": {
      "participation": [
        0,
        2,
        4,
        0,
        0,
        7,
        1,
        3,
        0,
        0,
        0,
        0,
        0,
        0,
        0,
        0,
        0,
        0,
        0,
        0,
        0,
        0,
        0,
        0,
        0,
        0,
        0,
        0,
        0,
        0,
        0,
        0,
        0,
        0,
        0,
        2,
        0,
        2,
        0,
        0,
        0,
        1,
        0,
        0,
        0,
        0,
        0,
        0,
        0,
        0,
        0,
        0
      ],
      "contributions": [
        "Any",
        "Bugfixes",
        "Features",
        "Ideas"
      ],
      "skills": [
        "Android",
        "Java",
        "Kotlin"
      ],
      "score": 70,
      "topics": [
        "ilus",
        "Java",
        "Colony"
      ]
    }
  },
  {
    "id": 1877,
    "name": "deimos",
    "full_name": "Mars/deimos",
    "html_url": "https://github.instance/Mars/deimos",
    "description": "Deimos is the smaller and outermost of the two natural satellites of Mars, the other being Phobos.",
    "created_at": "2019-03-15T13:48:14Z",
    "updated_at": "2019-09-27T11:23:23Z",
    "pushed_at": "2019-10-19T20:58:54Z",
    "stargazers_count": 0,
    "watchers_count": 0,
    "language": "Groovy",
    "forks_count": 4,
    "open_issues_count": 0,
    "license": null,
    "default_branch": "master",
    "owner": {
      "login": "Mars",
      "avatar_url": "./images/demo/Deimos.png"
    },
    "_InnerSourceMetadata": {
      "participation": [
        0,
        0,
        0,
        0,
        0,
        0,
        0,
        0,
        0,
        0,
        0,
        0,
        0,
        0,
        0,
        0,
        0,
        0,
        0,
        0,
        0,
        0,
        0,
        0,
        0,
        0,
        0,
        0,
        0,
        0,
        0,
        0,
        0,
        0,
        0,
        0,
        0,
        0,
        0,
        0,
        0,
        0,
        0,
        0,
        0,
        0,
        0,
        0,
        0,
        0,
        0,
        0
      ],
      "score": 70,
      "topics": [
        "deimos",
        "Groovy",
        "Mars"
      ]
    }
  },
  {
    "id": 1303,
    "name": "jupiter",
    "full_name": "Jupiter/jupiter",
    "html_url": "https://github.instance/Jupiter/jupiter",
    "description": "Jupiter is the fifth planet from the Sun and the largest in the Solar System.",
    "created_at": "2019-07-15T11:07:33Z",
    "updated_at": "2020-10-06T07:57:32Z",
    "pushed_at": "2020-10-07T04:50:56Z",
    "stargazers_count": 0,
    "watchers_count": 0,
    "language": "JavaScript",
    "forks_count": 0,
    "open_issues_count": 1,
    "license": null,
    "default_branch": "main",
    "owner": {
      "login": "Jupiter",
      "avatar_url": "./images/demo/Jupiter.png"
    },
    "_InnerSourceMetadata": {
      "participation": [
        4,
        4,
        2,
        0,
        0,
        0,
        0,
        7,
        0,
        1,
        0,
        0,
        0,
        2,
        1,
        1,
        0,
        3,
        0,
        0,
        0,
        0,
        0,
        0,
        5,
        0,
        3,
        2,
        2,
        5,
        3,
        1,
        0,
        0,
        0,
        2,
        0,
        0,
        0,
        0,
        0,
        0,
        2,
        0,
        1,
        0,
        3,
        0,
        0,
        0,
        1,
        7
      ],
      "score": 68,
      "topics": [
        "jupiter",
        "JavaScript",
        "Jupiter"
      ]
    }
  },
  {
    "id": 1672,
    "name": "rhea",
    "full_name": "Saturn/rhea",
    "html_url": "https://github.instance/Saturn/rhea",
    "description": "Rhea is the second-largest moon of Saturn and the ninth-largest moon in the Solar System.",
    "created_at": "2018-10-08T06:15:29Z",
    "updated_at": "2020-06-29T11:04:00Z",
    "pushed_at": "2020-06-04T18:34:56Z",
    "stargazers_count": 16,
    "watchers_count": 16,
    "language": "JavaScript",
    "forks_count": 7,
    "open_issues_count": 26,
    "license": null,
    "default_branch": "master",
    "owner": {
      "login": "Saturn",
      "avatar_url": "./images/demo/Saturn.png"
    },
    "_InnerSourceMetadata": {
      "participation": [
        0,
        0,
        1,
        0,
        0,
        0,
        1,
        0,
        0,
        0,
        0,
        0,
        0,
        0,
        0,
        0,
        0,
        0,
        0,
        0,
        0,
        0,
        0,
        0,
        0,
        0,
        0,
        0,
        0,
        0,
        0,
        0,
        0,
        0,
        0,
        0,
        0,
        0,
        0,
        0,
        0,
        0,
        0,
        0,
        0,
        0,
        0,
        0,
        0,
        0,
        0,
        0
      ],
      "logo": "./images/demo/Rhea.png",
      "score": 62,
      "topics": [
        "rhea",
        "JavaScript",
        "Saturn"
      ]
    }
  },
  {
    "id": 74321,
    "name": "tecoma",
    "full_name": "Colony/tecoma",
    "html_url": "https://github.instance/Colony/tecoma",
    "description": "The Tecoma system was one of the dead systems that was connected to the Ring network.",
    "created_at": "2019-08-12T08:10:12Z",
    "updated_at": "2020-10-07T07:56:16Z",
    "pushed_at": "2020-10-07T09:15:46Z",
    "stargazers_count": 0,
    "watchers_count": 0,
    "language": "JavaScript",
    "forks_count": 1,
    "open_issues_count": 0,
    "license": null,
    "default_branch": "master",
    "owner": {
      "login": "Colony",
      "avatar_url": "./images/demo/Tecoma.png"
    },
    "_InnerSourceMetadata": {
      "participation": [
        6,
        0,
        0,
        0,
        0,
        0,
        0,
        0,
        0,
        0,
        0,
        0,
        12,
        0,
        0,
        0,
        0,
        0,
        0,
        0,
        0,
        0,
        0,
        0,
        0,
        0,
        0,
        0,
        0,
        0,
        0,
        0,
        7,
        1,
        0,
        0,
        0,
        0,
        0,
        0,
        0,
        0,
        0,
        0,
        0,
        0,
        0,
        0,
        2,
        1,
        0,
        2
      ],
      "score": 59,
      "topics": [
        "tecoma",
        "JavaScript",
        "Colony"
      ]
    }
  },
  {
    "id": 1807,
    "name": "vesta",
    "full_name": "Belt/vesta",
    "html_url": "https://github.instance/Belt/vesta",
    "description": "Vesta is one of the largest objects in the asteroid belt.",
    "created_at": "2018-02-26T15:32:10Z",
    "updated_at": "2018-05-29T12:45:39Z",
    "pushed_at": "2018-04-27T12:39:17Z",
    "stargazers_count": 0,
    "watchers_count": 0,
    "language": "TypeScript",
    "forks_count": 1,
    "open_issues_count": 9,
    "license": null,
    "default_branch": "master",
    "owner": {
      "login": "Belt",
      "avatar_url": "./images/demo/Vesta.png"
    },
    "_InnerSourceMetadata": {
      "participation": [
        0,
        0,
        0,
        0,
        0,
        0,
        0,
        0,
        0,
        0,
        0,
        0,
        0,
        0,
        0,
        0,
        0,
        0,
        0,
        0,
        0,
        0,
        0,
        0,
        0,
        0,
        0,
        0,
        0,
        0,
        0,
        0,
        0,
        0,
        0,
        0,
        0,
        0,
        0,
        0,
        0,
        0,
        0,
        0,
        0,
        0,
        0,
        0,
        0,
        0,
        0,
        0
      ],
      "score": 57,
      "topics": [
        "vesta",
        "TypeScript",
        "Belt"
      ]
    }
  },
  {
    "id": 9378,
    "name": "phobos",
    "full_name": "Mars/phobos",
    "html_url": "https://github.instance/Mars/phobos",
    "description": "Phobos is the innermost and larger of the two natural satellites of Mars.",
    "created_at": "2017-10-31T02:32:41Z",
    "updated_at": "2020-03-27T14:17:48Z",
    "pushed_at": "2018-09-27T00:42:52Z",
    "stargazers_count": 1,
    "watchers_count": 1,
    "language": "TypeScript",
    "forks_count": 0,
    "open_issues_count": 17,
    "license": null,
    "default_branch": "develop",
    "owner": {
      "login": "Mars",
      "avatar_url": "./images/demo/Mars.png"
    },
    "_InnerSourceMetadata": {
      "participation": [
        0,
        0,
        0,
        0,
        0,
        0,
        0,
        0,
        0,
        0,
        0,
        0,
        0,
        0,
        0,
        0,
        0,
        0,
        0,
        0,
        0,
        0,
        0,
        0,
        0,
        0,
        0,
        0,
        0,
        0,
        0,
        0,
        0,
        0,
        0,
        0,
        0,
        0,
        0,
        0,
        0,
        0,
        0,
        0,
        0,
        0,
        0,
        0,
        0,
        0,
        0,
        0
      ],
      "logo": "./images/demo/Phobos.png",
      "score": 55,
      "topics": [
        "phobos",
        "TypeScript",
        "Mars"
      ]
    }
  },
  {
    "id": 1819,
    "name": "mimas",
    "full_name": "Saturn/mimas",
    "html_url": "https://github.instance/Saturn/mimas",
    "description": "Mimas, also designated Saturn I, is a moon of Saturn which was discovered in 1789 by William Herschel.",
    "created_at": "2019-04-04T13:57:38Z",
    "updated_at": "2019-06-18T10:16:00Z",
    "pushed_at": "2019-06-02T11:37:11Z",
    "stargazers_count": 0,
    "watchers_count": 0,
    "language": "Groovy",
    "forks_count": 0,
    "open_issues_count": 0,
    "license": null,
    "default_branch": "master",
    "owner": {
      "login": "Saturn",
      "avatar_url": "./images/demo/Saturn.png"
    },
    "_InnerSourceMetadata": {
      "participation": [
        0,
        0,
        0,
        0,
        0,
        0,
        0,
        0,
        0,
        0,
        0,
        0,
        0,
        0,
        0,
        0,
        0,
        0,
        0,
        0,
        0,
        0,
        0,
        0,
        0,
        0,
        0,
        0,
        0,
        0,
        0,
        0,
        0,
        0,
        0,
        0,
        0,
        0,
        0,
        0,
        0,
        0,
        0,
        0,
        0,
        0,
        0,
        0,
        0,
        0,
        0,
        0
      ],
      "score": 50,
      "logo": "./images/demo/Mimas.png",
      "topics": [
        "mimas",
        "Groovy",
        "Saturn"
      ]
    }
  },
  {
    "id": 57892,
    "name": "charon",
    "full_name": "Colony/charon",
    "html_url": "https://github.instance/Colony/charon",
    "description": "The Charon system is a dead system connected to the Ring network. Very little is known about this system.",
    "created_at": "2019-10-04T11:09:20Z",
    "updated_at": "2020-02-04T08:06:24Z",
    "pushed_at": "2019-11-11T15:04:31Z",
    "stargazers_count": 0,
    "watchers_count": 0,
    "language": "JavaScript",
    "forks_count": 0,
    "open_issues_count": 0,
    "license": null,
    "default_branch": "master",
    "owner": {
      "login": "Colony",
      "avatar_url": "./images/demo/Charon.png"
    },
    "_InnerSourceMetadata": {
      "participation": [
        0,
        0,
        0,
        3,
        1,
        0,
        0,
        0,
        0,
        0,
        0,
        0,
        0,
        0,
        0,
        0,
        0,
        0,
        0,
        0,
        0,
        0,
        0,
        0,
        0,
        0,
        0,
        0,
        0,
        0,
        0,
        0,
        0,
        0,
        0,
        0,
        0,
        0,
        0,
        0,
        0,
        0,
        0,
        0,
        0,
        0,
        0,
        0,
        0,
        0,
        0,
        0
      ],
      "score": 50,
      "topics": [
        "charon",
        "JavaScript",
        "Colony"
      ]
    }
  },
  {
    "id": 16101,
    "name": "callisto",
    "full_name": "Jupiter/callisto",
    "html_url": "https://github.instance/Jupiter/callisto",
    "description": "Callisto is the second-largest moon of Jupiter, after Ganymede.",
    "created_at": "2019-09-23T14:02:25Z",
    "updated_at": "2020-06-25T21:22:11Z",
    "pushed_at": "2020-04-16T10:14:27Z",
    "stargazers_count": 7,
    "watchers_count": 7,
    "language": null,
    "forks_count": 1,
    "open_issues_count": 16,
    "license": null,
    "default_branch": "master",
    "owner": {
      "login": "Jupiter",
      "avatar_url": "./images/demo/Callisto.png"
    },
    "_InnerSourceMetadata": {
      "participation": [
        0,
        1,
        0,
        0,
        3,
        1,
        0,
        7,
        0,
        0,
        0,
        0,
        0,
        0,
        0,
        2,
        0,
        0,
        0,
        0,
        0,
        0,
        0,
        0,
        0,
        0,
        0,
        2,
        0,
        0,
        0,
        0,
        0,
        0,
        0,
        0,
        0,
        0,
        0,
        0,
        0,
        0,
        0,
        0,
        0,
        0,
        0,
        0,
        0,
        0,
        0,
        0
      ],
      "score": 18,
      "topics": [
        "callisto",
        null,
        "Jupiter"
      ]
    }
  },
  {
    "id": 67343,
    "name": "adro",
    "full_name": "Colony/adro",
    "html_url": "https://github.instance/Colony/adro",
    "description": "The Adro system has a faint white dwarf star and no planets.",
    "created_at": "2017-10-10T12:25:00Z",
    "updated_at": "2018-10-26T06:24:46Z",
    "pushed_at": "2018-07-27T11:21:08Z",
    "stargazers_count": 0,
    "watchers_count": 0,
    "language": "JavaScript",
    "forks_count": 1,
    "open_issues_count": 0,
    "license": null,
    "default_branch": "master",
    "owner": {
      "login": "Colony",
      "avatar_url": "./images/demo/Adro.png"
    },
    "_InnerSourceMetadata": {
      "participation": [
        0,
        0,
        0,
        0,
        0,
        0,
        0,
        0,
        0,
        0,
        0,
        0,
        0,
        0,
        0,
        0,
        0,
        0,
        0,
        0,
        0,
        0,
        0,
        0,
        0,
        0,
        0,
        0,
        0,
        0,
        0,
        0,
        0,
        0,
        0,
        0,
        0,
        0,
        0,
        0,
        0,
        0,
        0,
        0,
        0,
        0,
        0,
        0,
        0,
        0,
        0,
        0
      ],
      "score": 5,
      "topics": [
        "adro",
        "JavaScript",
        "Colony"
      ]
    }
  },
  {
    "id": 5592,
    "name": "oshima",
    "full_name": "Belt/oshima",
    "html_url": "https://github.instance/Belt/oshima",
    "description": "Oshima is a Veritasian asteroid from the outer regions of the asteroid belt.",
    "created_at": "2018-05-23T10:13:05Z",
    "updated_at": "2018-06-12T07:15:48Z",
    "pushed_at": "2018-07-04T11:20:53Z",
    "stargazers_count": 0,
    "watchers_count": 0,
    "language": "ABAP",
    "forks_count": 0,
    "open_issues_count": 0,
    "license": null,
    "default_branch": "master",
    "owner": {
      "login": "Belt",
      "avatar_url": "./images/demo/Oshima.png"
    },
    "_InnerSourceMetadata": {
      "participation": [
        0,
        0,
        0,
        0,
        0,
        0,
        0,
        0,
        0,
        0,
        0,
        0,
        0,
        0,
        0,
        0,
        0,
        0,
        0,
        0,
        0,
        0,
        0,
        0,
        0,
        0,
        0,
        0,
        0,
        0,
        0,
        0,
        0,
        0,
        0,
        0,
        0,
        0,
        0,
        0,
        0,
        0,
        0,
        0,
        0,
        0,
        0,
        0,
        0,
        0,
        0,
        0
      ],
      "score": 0,
      "topics": [
        "oshima",
        "ABAP",
        "Belt"
      ]
    }
  }
]
